trace_event_pylog/__init__.py
trace_event_pylog/logger.py
trace_event_pylog-0.1.0.dist-info/licenses/LICENSE
trace_event_pylog-0.1.0.dist-info/METADATA
trace_event_pylog-0.1.0.dist-info/WHEEL
trace_event_pylog-0.1.0.dist-info/top_level.txt
trace_event_pylog-0.1.0.dist-info/RECORD
