Metadata-Version: 2.4
Name: trace_event_pylog
Version: 0.1.0
Summary: Asynchronous trace event logger with JSON output for performance analysis
Author-email: Matthew Khouzam <matthew.khouzam@gmail.com>
License: MIT
Project-URL: Homepage, https://github.com/TheMatthew/pylog
Project-URL: Bug Tracker, https://github.com/TheMatthew/pylog/issues
Requires-Python: >=3.8
License-File: LICENSE
Requires-Dist: ujson>=5.0.0
Dynamic: license-file
